evaluate_helper/__init__.py
evaluate_helper/metrics/__init__.py
evaluate_helper/metrics/average_metrics.py
evaluate_helper/metrics/custom_accuracy.py
evaluate_helper/metrics/mean_average_precision.py
evaluate_helper/metrics/psnr.py
evaluate_helper-0.0.1.dist-info/METADATA
evaluate_helper-0.0.1.dist-info/WHEEL
evaluate_helper-0.0.1.dist-info/top_level.txt
evaluate_helper-0.0.1.dist-info/RECORD
