Metadata-Version: 2.1
Name: evaluate-helper
Version: 0.0.1
Summary: Evaluate helper
Home-page: https://github.com/automatethem/evaluate-helper
Author: Sang Ki Kwon
Author-email: automatethem@gmail.com
License: MIT
Platform: UNKNOWN
Requires-Dist: evaluate
Requires-Dist: torchmetrics
